riceprint
