Metadata-Version: 1.1
Name: riceprint
Version: 1.4.0
Summary: OS-agnostic colored & custom Python console print() functions.
Home-page: https://github.com/ssriceboat/riceprint
Author: Kevin Sacca
Author-email: ssriceboat@gmail.com
License: MIT
Keywords: print console terminal shell python pprint color progress bar
Platform: UNKNOWN
Classifier: Development Status :: 4 - Beta
Classifier: Intended Audience :: Developers
Classifier: Topic :: Software Development :: Build Tools
Classifier: License :: OSI Approved :: MIT License
Classifier: Programming Language :: Python :: 3
Classifier: Programming Language :: Python :: 3.5
Classifier: Programming Language :: Python :: 3.6
Classifier: Programming Language :: Python :: 3.7
